pydantic_scrapeable_api_model/__init__.py
pydantic_scrapeable_api_model/py.typed
pydantic_scrapeable_api_model-3.2.0.dist-info/WHEEL
pydantic_scrapeable_api_model-3.2.0.dist-info/METADATA
pydantic_scrapeable_api_model-3.2.0.dist-info/RECORD
