Metadata-Version: 2.3
Name: pydantic-scrapeable-api-model
Version: 3.2.0
Summary: Minimal utilities to build scrapeable API models on top of Pydantic with simple caching and async HTTP.
Author: J.I. Cruz
Author-email: J.I. Cruz <ji@jicruz.com>
Requires-Dist: ji-async-http-utils>=5.0.0
Requires-Dist: pydantic-cacheable-model>=2.0.1
Requires-Python: >=3.10
